stock_analysis_program/__init__.py
stock_analysis_program/fetcher/__init__.py
stock_analysis_program/fetcher/financial_metrics_fetcher.py
stock_analysis_program/fetcher/revenue_growth_fetcher.py
stock_analysis_program/fetcher/stock_data_fetcher.py
stock_analysis_program/fetcher/stock_summary_fetcher.py
stock_analysis_program/main.py
stock_analysis_program/plotter/__init__.py
stock_analysis_program/plotter/current_prices_ticker_display.py
stock_analysis_program/plotter/financial_metrics_plotter.py
stock_analysis_program/plotter/revenue_growth_plotter.py
stock_analysis_program/plotter/stock_exchange_performance_plotter.py
stock_analysis_program/plotter/stock_price_plotter.py
stock_analysis_program/plotter/stock_volatility_plotter.py
stock_analysis_program-1.0.8.dist-info/LICENSE
stock_analysis_program-1.0.8.dist-info/METADATA
stock_analysis_program-1.0.8.dist-info/WHEEL
stock_analysis_program-1.0.8.dist-info/RECORD
